hallo_eltern_cli/__init__.py
hallo_eltern_cli/api.py
hallo_eltern_cli/cli.py
hallo_eltern_cli/commands/__init__.py
hallo_eltern_cli/commands/apicommand.py
hallo_eltern_cli/commands/basecommand.py
hallo_eltern_cli/commands/closecommand.py
hallo_eltern_cli/commands/configcommand.py
hallo_eltern_cli/commands/emailcommand.py
hallo_eltern_cli/commands/emailprocessorcommand.py
hallo_eltern_cli/commands/helpcommand.py
hallo_eltern_cli/commands/listcommand.py
hallo_eltern_cli/commands/mdacommand.py
hallo_eltern_cli/commands/opencommand.py
hallo_eltern_cli/commands/showcommand.py
hallo_eltern_cli/commands/smtpcommand.py
hallo_eltern_cli/commands/stdoutcommand.py
hallo_eltern_cli/commands/testcommand.py
hallo_eltern_cli/commands/versioncommand.py
hallo_eltern_cli/common.py
hallo_eltern_cli/idstore.py
hallo_eltern_cli/messagetoemailconverter.py
hallo_eltern_cli-1.1.0.dist-info/entry_points.txt
hallo_eltern_cli-1.1.0.dist-info/LICENSE.txt
hallo_eltern_cli-1.1.0.dist-info/WHEEL
hallo_eltern_cli-1.1.0.dist-info/METADATA
hallo_eltern_cli-1.1.0.dist-info/RECORD
