Metadata-Version: 2.1
Name: hallo-eltern-cli
Version: 1.1.0
Summary: Command-line/Python/Email interface for 'Hallo!Eltern' app for Upper-Austrian schools
Home-page: https://github.com/somechris/hallo-eltern-cli
License: Apache-2.0
Keywords: hallo,hallo eltern,api,email
Author: Christian Aistleitner
Author-email: christian@quelltextlich.at
Requires-Python: >=3.7
Classifier: Environment :: Console
Classifier: License :: OSI Approved :: Apache Software License
Classifier: Programming Language :: Python :: 3
Classifier: Programming Language :: Python :: 3.10
Classifier: Programming Language :: Python :: 3.7
Classifier: Programming Language :: Python :: 3.8
Classifier: Programming Language :: Python :: 3.9
Classifier: Topic :: Communications :: Email
Requires-Dist: requests (>=2.17.0,<3.0.0)
Project-URL: Bug Tracker, https://github.com/somechris/hallo-eltern-cli/issues
Project-URL: Repository, https://github.com/somechris/hallo-eltern-cli
